{
  "dropshadowsoft": {
    "shadowsoftsm": {
      "$value": [
        {
          "type": "dropShadow",
          "color": "rgba(0, 0, 0, 0.03999999910593033)",
          "offsetX": 0,
          "offsetY": 1,
          "radius": 4,
          "spread": 0,
          "blendMode": "MULTIPLY"
        },
        {
          "type": "dropShadow",
          "color": "rgba(0, 0, 0, 0.07999999821186066)",
          "offsetX": 0,
          "offsetY": 2,
          "radius": 6,
          "spread": 0,
          "blendMode": "LINEAR_BURN"
        }
      ],
      "value": [
        {
          "type": "dropShadow",
          "color": "rgba(0, 0, 0, 0.03999999910593033)",
          "offsetX": 0,
          "offsetY": 1,
          "radius": 4,
          "spread": 0,
          "blendMode": "MULTIPLY"
        },
        {
          "type": "dropShadow",
          "color": "rgba(0, 0, 0, 0.07999999821186066)",
          "offsetX": 0,
          "offsetY": 2,
          "radius": 6,
          "spread": 0,
          "blendMode": "LINEAR_BURN"
        }
      ],
      "type": "shadow",
      "$type": "shadow",
      "comment": "Broad and soft shadows with low contrast. Best for cards, sheets, or subtle surface separation.",
      "$extensions": {
        "com.figma": {
          "styleId": "S:0b02e84f03c817d8280c0471c86dc942e18e77f1,",
          "styleName": "Global/DropShadowSoft/shadowSoftSM"
        }
      },
      "filePath": "/home/user/vv-token-test-v3/tokens/brands/bild/semantic/effects/effects-dark.json",
      "isSource": true,
      "original": {
        "$value": [
          {
            "type": "dropShadow",
            "color": "rgba(0, 0, 0, 0.03999999910593033)",
            "offsetX": 0,
            "offsetY": 1,
            "radius": 4,
            "spread": 0,
            "blendMode": "MULTIPLY"
          },
          {
            "type": "dropShadow",
            "color": "rgba(0, 0, 0, 0.07999999821186066)",
            "offsetX": 0,
            "offsetY": 2,
            "radius": 6,
            "spread": 0,
            "blendMode": "LINEAR_BURN"
          }
        ],
        "value": [
          {
            "type": "dropShadow",
            "color": "rgba(0, 0, 0, 0.03999999910593033)",
            "offsetX": 0,
            "offsetY": 1,
            "radius": 4,
            "spread": 0,
            "blendMode": "MULTIPLY"
          },
          {
            "type": "dropShadow",
            "color": "rgba(0, 0, 0, 0.07999999821186066)",
            "offsetX": 0,
            "offsetY": 2,
            "radius": 6,
            "spread": 0,
            "blendMode": "LINEAR_BURN"
          }
        ],
        "type": "shadow",
        "$type": "shadow",
        "comment": "Broad and soft shadows with low contrast. Best for cards, sheets, or subtle surface separation.",
        "$extensions": {
          "com.figma": {
            "styleId": "S:0b02e84f03c817d8280c0471c86dc942e18e77f1,",
            "styleName": "Global/DropShadowSoft/shadowSoftSM"
          }
        }
      },
      "name": "DropshadowsoftShadowsoftsm",
      "attributes": {
        "category": "dropshadowsoft",
        "type": "shadowsoftsm"
      },
      "path": [
        "dropshadowsoft",
        "shadowsoftsm"
      ]
    },
    "shadowsoftmd": {
      "$value": [
        {
          "type": "dropShadow",
          "color": "rgba(0, 0, 0, 0.029999999329447746)",
          "offsetX": 0,
          "offsetY": 2,
          "radius": 16,
          "spread": 0,
          "blendMode": "MULTIPLY"
        },
        {
          "type": "dropShadow",
          "color": "rgba(0, 0, 0, 0.07000000029802322)",
          "offsetX": 0,
          "offsetY": 4,
          "radius": 12,
          "spread": 0,
          "blendMode": "LINEAR_BURN"
        }
      ],
      "value": [
        {
          "type": "dropShadow",
          "color": "rgba(0, 0, 0, 0.029999999329447746)",
          "offsetX": 0,
          "offsetY": 2,
          "radius": 16,
          "spread": 0,
          "blendMode": "MULTIPLY"
        },
        {
          "type": "dropShadow",
          "color": "rgba(0, 0, 0, 0.07000000029802322)",
          "offsetX": 0,
          "offsetY": 4,
          "radius": 12,
          "spread": 0,
          "blendMode": "LINEAR_BURN"
        }
      ],
      "type": "shadow",
      "$type": "shadow",
      "comment": "Broad and soft shadows with low contrast. Best for cards, sheets, or subtle surface separation.",
      "$extensions": {
        "com.figma": {
          "styleId": "S:4d1a81b6694aad9edfc26cfa54991096bcb619ea,",
          "styleName": "Global/DropShadowSoft/shadowSoftMD"
        }
      },
      "filePath": "/home/user/vv-token-test-v3/tokens/brands/bild/semantic/effects/effects-dark.json",
      "isSource": true,
      "original": {
        "$value": [
          {
            "type": "dropShadow",
            "color": "rgba(0, 0, 0, 0.029999999329447746)",
            "offsetX": 0,
            "offsetY": 2,
            "radius": 16,
            "spread": 0,
            "blendMode": "MULTIPLY"
          },
          {
            "type": "dropShadow",
            "color": "rgba(0, 0, 0, 0.07000000029802322)",
            "offsetX": 0,
            "offsetY": 4,
            "radius": 12,
            "spread": 0,
            "blendMode": "LINEAR_BURN"
          }
        ],
        "value": [
          {
            "type": "dropShadow",
            "color": "rgba(0, 0, 0, 0.029999999329447746)",
            "offsetX": 0,
            "offsetY": 2,
            "radius": 16,
            "spread": 0,
            "blendMode": "MULTIPLY"
          },
          {
            "type": "dropShadow",
            "color": "rgba(0, 0, 0, 0.07000000029802322)",
            "offsetX": 0,
            "offsetY": 4,
            "radius": 12,
            "spread": 0,
            "blendMode": "LINEAR_BURN"
          }
        ],
        "type": "shadow",
        "$type": "shadow",
        "comment": "Broad and soft shadows with low contrast. Best for cards, sheets, or subtle surface separation.",
        "$extensions": {
          "com.figma": {
            "styleId": "S:4d1a81b6694aad9edfc26cfa54991096bcb619ea,",
            "styleName": "Global/DropShadowSoft/shadowSoftMD"
          }
        }
      },
      "name": "DropshadowsoftShadowsoftmd",
      "attributes": {
        "category": "dropshadowsoft",
        "type": "shadowsoftmd"
      },
      "path": [
        "dropshadowsoft",
        "shadowsoftmd"
      ]
    },
    "shadowsoftlg": {
      "$value": [
        {
          "type": "dropShadow",
          "color": "rgba(0, 0, 0, 0.029999999329447746)",
          "offsetX": 0,
          "offsetY": 8,
          "radius": 24,
          "spread": 0,
          "blendMode": "LINEAR_BURN"
        },
        {
          "type": "dropShadow",
          "color": "rgba(0, 0, 0, 0.07000000029802322)",
          "offsetX": 0,
          "offsetY": 8,
          "radius": 16,
          "spread": 0,
          "blendMode": "LINEAR_BURN"
        }
      ],
      "value": [
        {
          "type": "dropShadow",
          "color": "rgba(0, 0, 0, 0.029999999329447746)",
          "offsetX": 0,
          "offsetY": 8,
          "radius": 24,
          "spread": 0,
          "blendMode": "LINEAR_BURN"
        },
        {
          "type": "dropShadow",
          "color": "rgba(0, 0, 0, 0.07000000029802322)",
          "offsetX": 0,
          "offsetY": 8,
          "radius": 16,
          "spread": 0,
          "blendMode": "LINEAR_BURN"
        }
      ],
      "type": "shadow",
      "$type": "shadow",
      "comment": "Broad and soft shadows with low contrast. Best for cards, sheets, or subtle surface separation.",
      "$extensions": {
        "com.figma": {
          "styleId": "S:6d95e6e2d4ba10697dd5406e0887c2ac9423a113,",
          "styleName": "Global/DropShadowSoft/shadowSoftLG"
        }
      },
      "filePath": "/home/user/vv-token-test-v3/tokens/brands/bild/semantic/effects/effects-dark.json",
      "isSource": true,
      "original": {
        "$value": [
          {
            "type": "dropShadow",
            "color": "rgba(0, 0, 0, 0.029999999329447746)",
            "offsetX": 0,
            "offsetY": 8,
            "radius": 24,
            "spread": 0,
            "blendMode": "LINEAR_BURN"
          },
          {
            "type": "dropShadow",
            "color": "rgba(0, 0, 0, 0.07000000029802322)",
            "offsetX": 0,
            "offsetY": 8,
            "radius": 16,
            "spread": 0,
            "blendMode": "LINEAR_BURN"
          }
        ],
        "value": [
          {
            "type": "dropShadow",
            "color": "rgba(0, 0, 0, 0.029999999329447746)",
            "offsetX": 0,
            "offsetY": 8,
            "radius": 24,
            "spread": 0,
            "blendMode": "LINEAR_BURN"
          },
          {
            "type": "dropShadow",
            "color": "rgba(0, 0, 0, 0.07000000029802322)",
            "offsetX": 0,
            "offsetY": 8,
            "radius": 16,
            "spread": 0,
            "blendMode": "LINEAR_BURN"
          }
        ],
        "type": "shadow",
        "$type": "shadow",
        "comment": "Broad and soft shadows with low contrast. Best for cards, sheets, or subtle surface separation.",
        "$extensions": {
          "com.figma": {
            "styleId": "S:6d95e6e2d4ba10697dd5406e0887c2ac9423a113,",
            "styleName": "Global/DropShadowSoft/shadowSoftLG"
          }
        }
      },
      "name": "DropshadowsoftShadowsoftlg",
      "attributes": {
        "category": "dropshadowsoft",
        "type": "shadowsoftlg"
      },
      "path": [
        "dropshadowsoft",
        "shadowsoftlg"
      ]
    },
    "shadowsoftxl": {
      "$value": [
        {
          "type": "dropShadow",
          "color": "rgba(0, 0, 0, 0.05000000074505806)",
          "offsetX": 0,
          "offsetY": 0,
          "radius": 64,
          "spread": 0,
          "blendMode": "LINEAR_BURN"
        },
        {
          "type": "dropShadow",
          "color": "rgba(0, 0, 0, 0.10000000149011612)",
          "offsetX": 0,
          "offsetY": 16,
          "radius": 32,
          "spread": 0,
          "blendMode": "LINEAR_BURN"
        }
      ],
      "value": [
        {
          "type": "dropShadow",
          "color": "rgba(0, 0, 0, 0.05000000074505806)",
          "offsetX": 0,
          "offsetY": 0,
          "radius": 64,
          "spread": 0,
          "blendMode": "LINEAR_BURN"
        },
        {
          "type": "dropShadow",
          "color": "rgba(0, 0, 0, 0.10000000149011612)",
          "offsetX": 0,
          "offsetY": 16,
          "radius": 32,
          "spread": 0,
          "blendMode": "LINEAR_BURN"
        }
      ],
      "type": "shadow",
      "$type": "shadow",
      "comment": "Broad and soft shadows with low contrast. Best for cards, sheets, or subtle surface separation.",
      "$extensions": {
        "com.figma": {
          "styleId": "S:1454904b263cbea328c17cd0077e0da81e2c8561,",
          "styleName": "Global/DropShadowSoft/shadowSoftXL"
        }
      },
      "filePath": "/home/user/vv-token-test-v3/tokens/brands/bild/semantic/effects/effects-dark.json",
      "isSource": true,
      "original": {
        "$value": [
          {
            "type": "dropShadow",
            "color": "rgba(0, 0, 0, 0.05000000074505806)",
            "offsetX": 0,
            "offsetY": 0,
            "radius": 64,
            "spread": 0,
            "blendMode": "LINEAR_BURN"
          },
          {
            "type": "dropShadow",
            "color": "rgba(0, 0, 0, 0.10000000149011612)",
            "offsetX": 0,
            "offsetY": 16,
            "radius": 32,
            "spread": 0,
            "blendMode": "LINEAR_BURN"
          }
        ],
        "value": [
          {
            "type": "dropShadow",
            "color": "rgba(0, 0, 0, 0.05000000074505806)",
            "offsetX": 0,
            "offsetY": 0,
            "radius": 64,
            "spread": 0,
            "blendMode": "LINEAR_BURN"
          },
          {
            "type": "dropShadow",
            "color": "rgba(0, 0, 0, 0.10000000149011612)",
            "offsetX": 0,
            "offsetY": 16,
            "radius": 32,
            "spread": 0,
            "blendMode": "LINEAR_BURN"
          }
        ],
        "type": "shadow",
        "$type": "shadow",
        "comment": "Broad and soft shadows with low contrast. Best for cards, sheets, or subtle surface separation.",
        "$extensions": {
          "com.figma": {
            "styleId": "S:1454904b263cbea328c17cd0077e0da81e2c8561,",
            "styleName": "Global/DropShadowSoft/shadowSoftXL"
          }
        }
      },
      "name": "DropshadowsoftShadowsoftxl",
      "attributes": {
        "category": "dropshadowsoft",
        "type": "shadowsoftxl"
      },
      "path": [
        "dropshadowsoft",
        "shadowsoftxl"
      ]
    }
  },
  "dropshadowhard": {
    "shadowhardsm": {
      "$value": [
        {
          "type": "dropShadow",
          "color": "rgba(0, 0, 0, 0.20000000298023224)",
          "offsetX": 0,
          "offsetY": 1,
          "radius": 2,
          "spread": 0,
          "blendMode": "NORMAL"
        },
        {
          "type": "dropShadow",
          "color": "rgba(0, 0, 0, 0.10000000149011612)",
          "offsetX": 0,
          "offsetY": 1,
          "radius": 3,
          "spread": 1,
          "blendMode": "LINEAR_BURN"
        }
      ],
      "value": [
        {
          "type": "dropShadow",
          "color": "rgba(0, 0, 0, 0.20000000298023224)",
          "offsetX": 0,
          "offsetY": 1,
          "radius": 2,
          "spread": 0,
          "blendMode": "NORMAL"
        },
        {
          "type": "dropShadow",
          "color": "rgba(0, 0, 0, 0.10000000149011612)",
          "offsetX": 0,
          "offsetY": 1,
          "radius": 3,
          "spread": 1,
          "blendMode": "LINEAR_BURN"
        }
      ],
      "type": "shadow",
      "$type": "shadow",
      "comment": "Sharper, higher-contrast shadows. Best for dialogs, modals, dropdowns and overlays that require stronger focus.",
      "$extensions": {
        "com.figma": {
          "styleId": "S:b1cc00467e7239838dcdb1ed376813d6c1d3bdd2,",
          "styleName": "Global/DropShadowHard/shadowHardSM"
        }
      },
      "filePath": "/home/user/vv-token-test-v3/tokens/brands/bild/semantic/effects/effects-dark.json",
      "isSource": true,
      "original": {
        "$value": [
          {
            "type": "dropShadow",
            "color": "rgba(0, 0, 0, 0.20000000298023224)",
            "offsetX": 0,
            "offsetY": 1,
            "radius": 2,
            "spread": 0,
            "blendMode": "NORMAL"
          },
          {
            "type": "dropShadow",
            "color": "rgba(0, 0, 0, 0.10000000149011612)",
            "offsetX": 0,
            "offsetY": 1,
            "radius": 3,
            "spread": 1,
            "blendMode": "LINEAR_BURN"
          }
        ],
        "value": [
          {
            "type": "dropShadow",
            "color": "rgba(0, 0, 0, 0.20000000298023224)",
            "offsetX": 0,
            "offsetY": 1,
            "radius": 2,
            "spread": 0,
            "blendMode": "NORMAL"
          },
          {
            "type": "dropShadow",
            "color": "rgba(0, 0, 0, 0.10000000149011612)",
            "offsetX": 0,
            "offsetY": 1,
            "radius": 3,
            "spread": 1,
            "blendMode": "LINEAR_BURN"
          }
        ],
        "type": "shadow",
        "$type": "shadow",
        "comment": "Sharper, higher-contrast shadows. Best for dialogs, modals, dropdowns and overlays that require stronger focus.",
        "$extensions": {
          "com.figma": {
            "styleId": "S:b1cc00467e7239838dcdb1ed376813d6c1d3bdd2,",
            "styleName": "Global/DropShadowHard/shadowHardSM"
          }
        }
      },
      "name": "DropshadowhardShadowhardsm",
      "attributes": {
        "category": "dropshadowhard",
        "type": "shadowhardsm"
      },
      "path": [
        "dropshadowhard",
        "shadowhardsm"
      ]
    },
    "shadowhardmd": {
      "$value": [
        {
          "type": "dropShadow",
          "color": "rgba(0, 0, 0, 0.10000000149011612)",
          "offsetX": 0,
          "offsetY": 4,
          "radius": 8,
          "spread": 0,
          "blendMode": "LINEAR_BURN"
        },
        {
          "type": "dropShadow",
          "color": "rgba(0, 0, 0, 0.1599999964237213)",
          "offsetX": 0,
          "offsetY": 2,
          "radius": 4,
          "spread": 0,
          "blendMode": "MULTIPLY"
        }
      ],
      "value": [
        {
          "type": "dropShadow",
          "color": "rgba(0, 0, 0, 0.10000000149011612)",
          "offsetX": 0,
          "offsetY": 4,
          "radius": 8,
          "spread": 0,
          "blendMode": "LINEAR_BURN"
        },
        {
          "type": "dropShadow",
          "color": "rgba(0, 0, 0, 0.1599999964237213)",
          "offsetX": 0,
          "offsetY": 2,
          "radius": 4,
          "spread": 0,
          "blendMode": "MULTIPLY"
        }
      ],
      "type": "shadow",
      "$type": "shadow",
      "comment": "Sharper, higher-contrast shadows. Best for dialogs, modals, dropdowns and overlays that require stronger focus.",
      "$extensions": {
        "com.figma": {
          "styleId": "S:c1a05d3395cb3fc489136aa2f0202d471b832f6a,",
          "styleName": "Global/DropShadowHard/shadowHardMD"
        }
      },
      "filePath": "/home/user/vv-token-test-v3/tokens/brands/bild/semantic/effects/effects-dark.json",
      "isSource": true,
      "original": {
        "$value": [
          {
            "type": "dropShadow",
            "color": "rgba(0, 0, 0, 0.10000000149011612)",
            "offsetX": 0,
            "offsetY": 4,
            "radius": 8,
            "spread": 0,
            "blendMode": "LINEAR_BURN"
          },
          {
            "type": "dropShadow",
            "color": "rgba(0, 0, 0, 0.1599999964237213)",
            "offsetX": 0,
            "offsetY": 2,
            "radius": 4,
            "spread": 0,
            "blendMode": "MULTIPLY"
          }
        ],
        "value": [
          {
            "type": "dropShadow",
            "color": "rgba(0, 0, 0, 0.10000000149011612)",
            "offsetX": 0,
            "offsetY": 4,
            "radius": 8,
            "spread": 0,
            "blendMode": "LINEAR_BURN"
          },
          {
            "type": "dropShadow",
            "color": "rgba(0, 0, 0, 0.1599999964237213)",
            "offsetX": 0,
            "offsetY": 2,
            "radius": 4,
            "spread": 0,
            "blendMode": "MULTIPLY"
          }
        ],
        "type": "shadow",
        "$type": "shadow",
        "comment": "Sharper, higher-contrast shadows. Best for dialogs, modals, dropdowns and overlays that require stronger focus.",
        "$extensions": {
          "com.figma": {
            "styleId": "S:c1a05d3395cb3fc489136aa2f0202d471b832f6a,",
            "styleName": "Global/DropShadowHard/shadowHardMD"
          }
        }
      },
      "name": "DropshadowhardShadowhardmd",
      "attributes": {
        "category": "dropshadowhard",
        "type": "shadowhardmd"
      },
      "path": [
        "dropshadowhard",
        "shadowhardmd"
      ]
    },
    "shadowhardlg": {
      "$value": [
        {
          "type": "dropShadow",
          "color": "rgba(0, 0, 0, 0.20000000298023224)",
          "offsetX": 0,
          "offsetY": 2,
          "radius": 3,
          "spread": 0,
          "blendMode": "NORMAL"
        },
        {
          "type": "dropShadow",
          "color": "rgba(0, 0, 0, 0.10000000149011612)",
          "offsetX": 0,
          "offsetY": 6,
          "radius": 10,
          "spread": 4,
          "blendMode": "LINEAR_BURN"
        }
      ],
      "value": [
        {
          "type": "dropShadow",
          "color": "rgba(0, 0, 0, 0.20000000298023224)",
          "offsetX": 0,
          "offsetY": 2,
          "radius": 3,
          "spread": 0,
          "blendMode": "NORMAL"
        },
        {
          "type": "dropShadow",
          "color": "rgba(0, 0, 0, 0.10000000149011612)",
          "offsetX": 0,
          "offsetY": 6,
          "radius": 10,
          "spread": 4,
          "blendMode": "LINEAR_BURN"
        }
      ],
      "type": "shadow",
      "$type": "shadow",
      "comment": "Sharper, higher-contrast shadows. Best for dialogs, modals, dropdowns and overlays that require stronger focus.",
      "$extensions": {
        "com.figma": {
          "styleId": "S:d1813d3e2c9b7b28971862752d79399f5432831d,",
          "styleName": "Global/DropShadowHard/shadowHardLG"
        }
      },
      "filePath": "/home/user/vv-token-test-v3/tokens/brands/bild/semantic/effects/effects-dark.json",
      "isSource": true,
      "original": {
        "$value": [
          {
            "type": "dropShadow",
            "color": "rgba(0, 0, 0, 0.20000000298023224)",
            "offsetX": 0,
            "offsetY": 2,
            "radius": 3,
            "spread": 0,
            "blendMode": "NORMAL"
          },
          {
            "type": "dropShadow",
            "color": "rgba(0, 0, 0, 0.10000000149011612)",
            "offsetX": 0,
            "offsetY": 6,
            "radius": 10,
            "spread": 4,
            "blendMode": "LINEAR_BURN"
          }
        ],
        "value": [
          {
            "type": "dropShadow",
            "color": "rgba(0, 0, 0, 0.20000000298023224)",
            "offsetX": 0,
            "offsetY": 2,
            "radius": 3,
            "spread": 0,
            "blendMode": "NORMAL"
          },
          {
            "type": "dropShadow",
            "color": "rgba(0, 0, 0, 0.10000000149011612)",
            "offsetX": 0,
            "offsetY": 6,
            "radius": 10,
            "spread": 4,
            "blendMode": "LINEAR_BURN"
          }
        ],
        "type": "shadow",
        "$type": "shadow",
        "comment": "Sharper, higher-contrast shadows. Best for dialogs, modals, dropdowns and overlays that require stronger focus.",
        "$extensions": {
          "com.figma": {
            "styleId": "S:d1813d3e2c9b7b28971862752d79399f5432831d,",
            "styleName": "Global/DropShadowHard/shadowHardLG"
          }
        }
      },
      "name": "DropshadowhardShadowhardlg",
      "attributes": {
        "category": "dropshadowhard",
        "type": "shadowhardlg"
      },
      "path": [
        "dropshadowhard",
        "shadowhardlg"
      ]
    },
    "shadowhardxl": {
      "$value": [
        {
          "type": "dropShadow",
          "color": "rgba(0, 0, 0, 0.20000000298023224)",
          "offsetX": 0,
          "offsetY": 4,
          "radius": 4,
          "spread": 0,
          "blendMode": "DARKEN"
        },
        {
          "type": "dropShadow",
          "color": "rgba(0, 0, 0, 0.10000000149011612)",
          "offsetX": 0,
          "offsetY": 8,
          "radius": 12,
          "spread": 6,
          "blendMode": "LINEAR_BURN"
        }
      ],
      "value": [
        {
          "type": "dropShadow",
          "color": "rgba(0, 0, 0, 0.20000000298023224)",
          "offsetX": 0,
          "offsetY": 4,
          "radius": 4,
          "spread": 0,
          "blendMode": "DARKEN"
        },
        {
          "type": "dropShadow",
          "color": "rgba(0, 0, 0, 0.10000000149011612)",
          "offsetX": 0,
          "offsetY": 8,
          "radius": 12,
          "spread": 6,
          "blendMode": "LINEAR_BURN"
        }
      ],
      "type": "shadow",
      "$type": "shadow",
      "comment": "Sharper, higher-contrast shadows. Best for dialogs, modals, dropdowns and overlays that require stronger focus.",
      "$extensions": {
        "com.figma": {
          "styleId": "S:0827f80a0b51f48f992b59b426a1aa12e5d51915,",
          "styleName": "Global/DropShadowHard/shadowHardXL"
        }
      },
      "filePath": "/home/user/vv-token-test-v3/tokens/brands/bild/semantic/effects/effects-dark.json",
      "isSource": true,
      "original": {
        "$value": [
          {
            "type": "dropShadow",
            "color": "rgba(0, 0, 0, 0.20000000298023224)",
            "offsetX": 0,
            "offsetY": 4,
            "radius": 4,
            "spread": 0,
            "blendMode": "DARKEN"
          },
          {
            "type": "dropShadow",
            "color": "rgba(0, 0, 0, 0.10000000149011612)",
            "offsetX": 0,
            "offsetY": 8,
            "radius": 12,
            "spread": 6,
            "blendMode": "LINEAR_BURN"
          }
        ],
        "value": [
          {
            "type": "dropShadow",
            "color": "rgba(0, 0, 0, 0.20000000298023224)",
            "offsetX": 0,
            "offsetY": 4,
            "radius": 4,
            "spread": 0,
            "blendMode": "DARKEN"
          },
          {
            "type": "dropShadow",
            "color": "rgba(0, 0, 0, 0.10000000149011612)",
            "offsetX": 0,
            "offsetY": 8,
            "radius": 12,
            "spread": 6,
            "blendMode": "LINEAR_BURN"
          }
        ],
        "type": "shadow",
        "$type": "shadow",
        "comment": "Sharper, higher-contrast shadows. Best for dialogs, modals, dropdowns and overlays that require stronger focus.",
        "$extensions": {
          "com.figma": {
            "styleId": "S:0827f80a0b51f48f992b59b426a1aa12e5d51915,",
            "styleName": "Global/DropShadowHard/shadowHardXL"
          }
        }
      },
      "name": "DropshadowhardShadowhardxl",
      "attributes": {
        "category": "dropshadowhard",
        "type": "shadowhardxl"
      },
      "path": [
        "dropshadowhard",
        "shadowhardxl"
      ]
    }
  },
  "alert": {
    "alertshadowdown": {
      "$value": [
        {
          "type": "dropShadow",
          "color": "rgba(0, 0, 0, 0.20000000298023224)",
          "offsetX": 0,
          "offsetY": 6,
          "radius": 10,
          "spread": 0,
          "blendMode": "LINEAR_BURN"
        }
      ],
      "value": [
        {
          "type": "dropShadow",
          "color": "rgba(0, 0, 0, 0.20000000298023224)",
          "offsetX": 0,
          "offsetY": 6,
          "radius": 10,
          "spread": 0,
          "blendMode": "LINEAR_BURN"
        }
      ],
      "type": "shadow",
      "$type": "shadow",
      "comment": "",
      "$extensions": {
        "com.figma": {
          "styleId": "S:bb635123865da4a69542edaee7bacd008ac1c4af,",
          "styleName": "Component/Alert/alertShadowDown"
        }
      },
      "filePath": "/home/user/vv-token-test-v3/tokens/brands/bild/semantic/effects/effects-dark.json",
      "isSource": true,
      "original": {
        "$value": [
          {
            "type": "dropShadow",
            "color": "rgba(0, 0, 0, 0.20000000298023224)",
            "offsetX": 0,
            "offsetY": 6,
            "radius": 10,
            "spread": 0,
            "blendMode": "LINEAR_BURN"
          }
        ],
        "value": [
          {
            "type": "dropShadow",
            "color": "rgba(0, 0, 0, 0.20000000298023224)",
            "offsetX": 0,
            "offsetY": 6,
            "radius": 10,
            "spread": 0,
            "blendMode": "LINEAR_BURN"
          }
        ],
        "type": "shadow",
        "$type": "shadow",
        "comment": "",
        "$extensions": {
          "com.figma": {
            "styleId": "S:bb635123865da4a69542edaee7bacd008ac1c4af,",
            "styleName": "Component/Alert/alertShadowDown"
          }
        }
      },
      "name": "AlertAlertshadowdown",
      "attributes": {
        "category": "alert",
        "type": "alertshadowdown"
      },
      "path": [
        "alert",
        "alertshadowdown"
      ]
    },
    "alertshadowup": {
      "$value": [
        {
          "type": "dropShadow",
          "color": "rgba(0, 0, 0, 0.20000000298023224)",
          "offsetX": 0,
          "offsetY": -2,
          "radius": 10,
          "spread": 0,
          "blendMode": "LINEAR_BURN"
        }
      ],
      "value": [
        {
          "type": "dropShadow",
          "color": "rgba(0, 0, 0, 0.20000000298023224)",
          "offsetX": 0,
          "offsetY": -2,
          "radius": 10,
          "spread": 0,
          "blendMode": "LINEAR_BURN"
        }
      ],
      "type": "shadow",
      "$type": "shadow",
      "comment": "",
      "$extensions": {
        "com.figma": {
          "styleId": "S:aa8f6212e74ef6b114706d8a39ff6a9b94aaaffe,",
          "styleName": "Component/Alert/alertShadowUp"
        }
      },
      "filePath": "/home/user/vv-token-test-v3/tokens/brands/bild/semantic/effects/effects-dark.json",
      "isSource": true,
      "original": {
        "$value": [
          {
            "type": "dropShadow",
            "color": "rgba(0, 0, 0, 0.20000000298023224)",
            "offsetX": 0,
            "offsetY": -2,
            "radius": 10,
            "spread": 0,
            "blendMode": "LINEAR_BURN"
          }
        ],
        "value": [
          {
            "type": "dropShadow",
            "color": "rgba(0, 0, 0, 0.20000000298023224)",
            "offsetX": 0,
            "offsetY": -2,
            "radius": 10,
            "spread": 0,
            "blendMode": "LINEAR_BURN"
          }
        ],
        "type": "shadow",
        "$type": "shadow",
        "comment": "",
        "$extensions": {
          "com.figma": {
            "styleId": "S:aa8f6212e74ef6b114706d8a39ff6a9b94aaaffe,",
            "styleName": "Component/Alert/alertShadowUp"
          }
        }
      },
      "name": "AlertAlertshadowup",
      "attributes": {
        "category": "alert",
        "type": "alertshadowup"
      },
      "path": [
        "alert",
        "alertshadowup"
      ]
    }
  },
  "menu": {
    "menushadow": {
      "$value": [
        {
          "type": "dropShadow",
          "color": "rgba(0, 0, 0, 0.10000000149011612)",
          "offsetX": 0,
          "offsetY": 8,
          "radius": 10,
          "spread": -8,
          "blendMode": "LINEAR_BURN"
        }
      ],
      "value": [
        {
          "type": "dropShadow",
          "color": "rgba(0, 0, 0, 0.10000000149011612)",
          "offsetX": 0,
          "offsetY": 8,
          "radius": 10,
          "spread": -8,
          "blendMode": "LINEAR_BURN"
        }
      ],
      "type": "shadow",
      "$type": "shadow",
      "comment": "",
      "$extensions": {
        "com.figma": {
          "styleId": "S:fb9aab619337d9b3aa2138b720bf9d1bc91d9932,",
          "styleName": "Component/Menu/menuShadow"
        }
      },
      "filePath": "/home/user/vv-token-test-v3/tokens/brands/bild/semantic/effects/effects-dark.json",
      "isSource": true,
      "original": {
        "$value": [
          {
            "type": "dropShadow",
            "color": "rgba(0, 0, 0, 0.10000000149011612)",
            "offsetX": 0,
            "offsetY": 8,
            "radius": 10,
            "spread": -8,
            "blendMode": "LINEAR_BURN"
          }
        ],
        "value": [
          {
            "type": "dropShadow",
            "color": "rgba(0, 0, 0, 0.10000000149011612)",
            "offsetX": 0,
            "offsetY": 8,
            "radius": 10,
            "spread": -8,
            "blendMode": "LINEAR_BURN"
          }
        ],
        "type": "shadow",
        "$type": "shadow",
        "comment": "",
        "$extensions": {
          "com.figma": {
            "styleId": "S:fb9aab619337d9b3aa2138b720bf9d1bc91d9932,",
            "styleName": "Component/Menu/menuShadow"
          }
        }
      },
      "name": "MenuMenushadow",
      "attributes": {
        "category": "menu",
        "type": "menushadow"
      },
      "path": [
        "menu",
        "menushadow"
      ]
    },
    "heyinputshadow": {
      "$value": [
        {
          "type": "dropShadow",
          "color": "rgba(0, 0, 0, 0)",
          "offsetX": 0,
          "offsetY": 8,
          "radius": 10,
          "spread": -8,
          "blendMode": "LINEAR_BURN"
        }
      ],
      "value": [
        {
          "type": "dropShadow",
          "color": "rgba(0, 0, 0, 0)",
          "offsetX": 0,
          "offsetY": 8,
          "radius": 10,
          "spread": -8,
          "blendMode": "LINEAR_BURN"
        }
      ],
      "type": "shadow",
      "$type": "shadow",
      "comment": "",
      "$extensions": {
        "com.figma": {
          "styleId": "S:114517e8a24621d1bc4d8dede9e3e65b690f5896,",
          "styleName": "Component/Menu/heyInputShadow"
        }
      },
      "filePath": "/home/user/vv-token-test-v3/tokens/brands/bild/semantic/effects/effects-dark.json",
      "isSource": true,
      "original": {
        "$value": [
          {
            "type": "dropShadow",
            "color": "rgba(0, 0, 0, 0)",
            "offsetX": 0,
            "offsetY": 8,
            "radius": 10,
            "spread": -8,
            "blendMode": "LINEAR_BURN"
          }
        ],
        "value": [
          {
            "type": "dropShadow",
            "color": "rgba(0, 0, 0, 0)",
            "offsetX": 0,
            "offsetY": 8,
            "radius": 10,
            "spread": -8,
            "blendMode": "LINEAR_BURN"
          }
        ],
        "type": "shadow",
        "$type": "shadow",
        "comment": "",
        "$extensions": {
          "com.figma": {
            "styleId": "S:114517e8a24621d1bc4d8dede9e3e65b690f5896,",
            "styleName": "Component/Menu/heyInputShadow"
          }
        }
      },
      "name": "MenuHeyinputshadow",
      "attributes": {
        "category": "menu",
        "type": "heyinputshadow"
      },
      "path": [
        "menu",
        "heyinputshadow"
      ]
    }
  },
  "teaser": {
    "teaserheadlinesshadow": {
      "$value": [
        {
          "type": "dropShadow",
          "color": "rgba(0, 0, 0, 0.6000000238418579)",
          "offsetX": 0,
          "offsetY": 2,
          "radius": 8,
          "spread": 0,
          "blendMode": "NORMAL"
        }
      ],
      "value": [
        {
          "type": "dropShadow",
          "color": "rgba(0, 0, 0, 0.6000000238418579)",
          "offsetX": 0,
          "offsetY": 2,
          "radius": 8,
          "spread": 0,
          "blendMode": "NORMAL"
        }
      ],
      "type": "shadow",
      "$type": "shadow",
      "comment": "",
      "$extensions": {
        "com.figma": {
          "styleId": "S:60bfa781daf152877a92cf70586a7e62fd3aee7b,",
          "styleName": "Component/Teaser/teaserHeadlinesShadow"
        }
      },
      "filePath": "/home/user/vv-token-test-v3/tokens/brands/bild/semantic/effects/effects-dark.json",
      "isSource": true,
      "original": {
        "$value": [
          {
            "type": "dropShadow",
            "color": "rgba(0, 0, 0, 0.6000000238418579)",
            "offsetX": 0,
            "offsetY": 2,
            "radius": 8,
            "spread": 0,
            "blendMode": "NORMAL"
          }
        ],
        "value": [
          {
            "type": "dropShadow",
            "color": "rgba(0, 0, 0, 0.6000000238418579)",
            "offsetX": 0,
            "offsetY": 2,
            "radius": 8,
            "spread": 0,
            "blendMode": "NORMAL"
          }
        ],
        "type": "shadow",
        "$type": "shadow",
        "comment": "",
        "$extensions": {
          "com.figma": {
            "styleId": "S:60bfa781daf152877a92cf70586a7e62fd3aee7b,",
            "styleName": "Component/Teaser/teaserHeadlinesShadow"
          }
        }
      },
      "name": "TeaserTeaserheadlinesshadow",
      "attributes": {
        "category": "teaser",
        "type": "teaserheadlinesshadow"
      },
      "path": [
        "teaser",
        "teaserheadlinesshadow"
      ]
    }
  }
}
